autodist/__init__.py
autodist/autodist.py
autodist/cluster.py
autodist/const.py
autodist/coordinator.py
autodist/graph_item.py
autodist/patch.py
autodist/remapper.py
autodist/resource_spec.py
autodist/runner.py
autodist/checkpoint/__init__.py
autodist/checkpoint/saved_model_builder.py
autodist/checkpoint/saver.py
autodist/kernel/__init__.py
autodist/kernel/graph_transformer.py
autodist/kernel/kernel.py
autodist/kernel/partitioner.py
autodist/kernel/replicator.py
autodist/kernel/common/__init__.py
autodist/kernel/common/op_info.py
autodist/kernel/common/proxy_variable.py
autodist/kernel/common/utils.py
autodist/kernel/common/variable_utils.py
autodist/kernel/device/__init__.py
autodist/kernel/device/resolver.py
autodist/kernel/synchronization/__init__.py
autodist/kernel/synchronization/all_reduce_synchronizer.py
autodist/kernel/synchronization/collective_key.py
autodist/kernel/synchronization/compressor.py
autodist/kernel/synchronization/ps_synchronizer.py
autodist/kernel/synchronization/synchronizer.py
autodist/proto/__init__.py
autodist/proto/graphitem_pb2.py
autodist/proto/strategy_pb2.py
autodist/proto/synchronizers_pb2.py
autodist/strategy/__init__.py
autodist/strategy/all_reduce_strategy.py
autodist/strategy/base.py
autodist/strategy/parallax_strategy.py
autodist/strategy/partitioned_all_reduce_strategy.py
autodist/strategy/partitioned_ps_strategy.py
autodist/strategy/ps_lb_strategy.py
autodist/strategy/ps_strategy.py
autodist/strategy/random_axis_partition_all_reduce_strategy.py
autodist/strategy/uneven_partition_ps_strategy.py
autodist/utils/__init__.py
autodist/utils/logging.py
autodist/utils/network.py
autodist/utils/server_starter.py
autodist/utils/visualization_util.py
autodist-0.7.0rc2.dist-info/LICENSE
autodist-0.7.0rc2.dist-info/METADATA
autodist-0.7.0rc2.dist-info/WHEEL
autodist-0.7.0rc2.dist-info/top_level.txt
autodist-0.7.0rc2.dist-info/RECORD
