Metadata-Version: 2.1
Name: autodist
Version: 0.7.0rc2
Summary: AutoDist is a distributed deep-learning training engine.
Home-page: https://github.com/petuum/autodist
Author: Petuum Inc. & The AutoDist Authors
Author-email: 
License: UNKNOWN
Platform: UNKNOWN
Classifier: Programming Language :: Python :: 3
Classifier: Topic :: Scientific/Engineering :: Artificial Intelligence
Requires-Python: >=3.6
Requires-Dist: netifaces (==0.10.9)
Requires-Dist: numpy
Requires-Dist: paramiko
Requires-Dist: protobuf (==3.11.0)
Requires-Dist: pyyaml
Provides-Extra: dev
Requires-Dist: pytest ; extra == 'dev'
Requires-Dist: pytest-cov ; extra == 'dev'
Requires-Dist: pydocstyle ; extra == 'dev'
Requires-Dist: prospector ; extra == 'dev'
